pytest_dbt_core/__init__.py
pytest_dbt_core/_version.py
pytest_dbt_core/fixtures.py
pytest_dbt_core/plugin.py
pytest_dbt_core-0.2.4.dist-info/LICENSE
pytest_dbt_core-0.2.4.dist-info/METADATA
pytest_dbt_core-0.2.4.dist-info/WHEEL
pytest_dbt_core-0.2.4.dist-info/entry_points.txt
pytest_dbt_core-0.2.4.dist-info/top_level.txt
pytest_dbt_core-0.2.4.dist-info/RECORD
