Metadata-Version: 2.1
Name: pytest-dbt-core
Version: 0.2.4
Summary: Pytest extension for dbt.
Home-page: https://github.com/godatadriven/pytest-dbt-core
Author: Cor Zuurmond
Maintainer: Cor Zuurmond
Maintainer-email: corzuurmond@godatadriven.com
License: Apache 2.0
Project-URL: Source, https://github.com/godatadriven/pytest-dbt-core
Project-URL: Tracker, https://github.com/godatadriven/pytest-dbt-core/issues
Keywords: dbt,SQL,data,data transformation,testing,pytest
Platform: any
Classifier: Framework :: Pytest
Requires-Python: >=3.7
License-File: LICENSE
Requires-Dist: dbt-core >=1.0.0
Provides-Extra: test
Requires-Dist: dbt-spark[odbc] <1.9.0,>=1.1.0 ; extra == 'test'
Requires-Dist: pyspark <4.0.0,>=3.0.0 ; extra == 'test'
Requires-Dist: pre-commit >=2.14.1 ; extra == 'test'
Requires-Dist: pytest >=6.2.5 ; extra == 'test'
Requires-Dist: pytest-spark >=0.6.0 ; extra == 'test'
Requires-Dist: pytest-cov >=2.12.1 ; extra == 'test'
